{"result": [{"x": 1, "y": 67764}, {"x": 2, "y": 93406}, {"x": 3, "y": 37824}, {"x": 4, "y": 44203}, {"x": 5, "y": 4332}, {"x": 6, "y": 22477}, {"x": 7, "y": 53889}, {"x": 8, "y": 32067}, {"x": 9, "y": 91732}, {"x": 10, "y": 73098}, {"x": 11, "y": 31074}, {"x": 12, "y": 49497}, {"x": 13, "y": 3016}, {"x": 14, "y": 11600}, {"x": 15, "y": 36502}, {"x": 16, "y": 46579}, {"x": 17, "y": 66137}, {"x": 18, "y": 33486}, {"x": 19, "y": 84721}, {"x": 20, "y": 66348}, {"x": 21, "y": 33449}, {"x": 22, "y": 46727}, {"x": 23, "y": 60898}, {"x": 24, "y": 69538}, {"x": 25, "y": 76923}, {"x": 26, "y": 83702}, {"x": 27, "y": 97154}, {"x": 28, "y": 53532}, {"x": 29, "y": 2250}, {"x": 30, "y": 47738}, {"x": 31, "y": 53095}, {"x": 32, "y": 82712}, {"x": 33, "y": 57176}, {"x": 34, "y": 55106}, {"x": 35, "y": 35022}, {"x": 36, "y": 27084}, {"x": 37, "y": 60191}, {"x": 38, "y": 61817}, {"x": 39, "y": 94173}, {"x": 40, "y": 55253}, {"x": 41, "y": 54860}, {"x": 42, "y": 82866}, {"x": 43, "y": 59600}, {"x": 44, "y": 73409}, {"x": 45, "y": 6388}, {"x": 46, "y": 50346}, {"x": 47, "y": 63311}, {"x": 48, "y": 80751}, {"x": 49, "y": 50241}, {"x": 50, "y": 9936}, {"x": 51, "y": 78149}, {"x": 52, "y": 99865}, {"x": 53, "y": 70367}, {"x": 54, "y": 14311}, {"x": 55, "y": 30222}, {"x": 56, "y": 24202}, {"x": 57, "y": 61019}, {"x": 58, "y": 42689}, {"x": 59, "y": 14249}, {"x": 60, "y": 27158}, {"x": 61, "y": 18142}, {"x": 62, "y": 26076}, {"x": 63, "y": 44575}, {"x": 64, "y": 91924}, {"x": 65, "y": 43010}, {"x": 66, "y": 3659}, {"x": 67, "y": 67262}, {"x": 68, "y": 23466}, {"x": 69, "y": 7077}, {"x": 70, "y": 23944}, {"x": 71, "y": 75369}, {"x": 72, "y": 13688}, {"x": 73, "y": 69143}, {"x": 74, "y": 76417}, {"x": 75, "y": 60716}, {"x": 76, "y": 60892}, {"x": 77, "y": 46559}, {"x": 78, "y": 66820}, {"x": 79, "y": 78904}, {"x": 80, "y": 20833}, {"x": 81, "y": 37407}, {"x": 82, "y": 1845}, {"x": 83, "y": 20686}, {"x": 84, "y": 27699}, {"x": 85, "y": 23302}, {"x": 86, "y": 49657}, {"x": 87, "y": 43853}, {"x": 88, "y": 24673}, {"x": 89, "y": 26686}, {"x": 90, "y": 3094}, {"x": 91, "y": 25860}, {"x": 92, "y": 85940}, {"x": 93, "y": 67347}, {"x": 94, "y": 27238}, {"x": 95, "y": 62824}, {"x": 96, "y": 35506}, {"x": 97, "y": 79306}, {"x": 98, "y": 65881}, {"x": 99, "y": 13188}, {"x": 100, "y": 9012}, {"x": 101, "y": 88672}, {"x": 102, "y": 23564}, {"x": 103, "y": 14453}, {"x": 104, "y": 30035}, {"x": 105, "y": 27789}, {"x": 106, "y": 57926}, {"x": 107, "y": 94981}, {"x": 108, "y": 27990}, {"x": 109, "y": 26199}, {"x": 110, "y": 42217}, {"x": 111, "y": 82196}, {"x": 112, "y": 75936}, {"x": 113, "y": 85373}, {"x": 115, "y": 18334}, {"x": 116, "y": 69000}, {"x": 117, "y": 24056}, {"x": 118, "y": 95240}, {"x": 119, "y": 29219}, {"x": 120, "y": 98771}, {"x": 121, "y": 33867}, {"x": 123, "y": 8213}, {"x": 124, "y": 59673}, {"x": 126, "y": 69183}, {"x": 127, "y": 59289}, {"x": 128, "y": 17759}, {"x": 130, "y": 77608}, {"x": 131, "y": 70257}, {"x": 132, "y": 49202}, {"x": 133, "y": 20200}, {"x": 134, "y": 29845}, {"x": 135, "y": 48313}, {"x": 136, "y": 84747}, {"x": 137, "y": 119}, {"x": 138, "y": 51753}, {"x": 139, "y": 21010}, {"x": 140, "y": 59631}, {"x": 143, "y": 37835}, {"x": 145, "y": 88876}, {"x": 147, "y": 49795}, {"x": 148, "y": 87357}, {"x": 150, "y": 18348}, {"x": 151, "y": 89810}, {"x": 152, "y": 18005}, {"x": 153, "y": 98918}, {"x": 154, "y": 373}, {"x": 156, "y": 8685}, {"x": 158, "y": 82765}, {"x": 160, "y": 84219}, {"x": 161, "y": 54350}, {"x": 162, "y": 17680}, {"x": 163, "y": 57672}, {"x": 164, "y": 2103}, {"x": 166, "y": 66271}, {"x": 168, "y": 95746}, {"x": 169, "y": 57919}, {"x": 170, "y": 85180}, {"x": 171, "y": 13295}, {"x": 172, "y": 53507}, {"x": 173, "y": 20499}, {"x": 176, "y": 86769}, {"x": 177, "y": 77094}, {"x": 180, "y": 74396}, {"x": 182, "y": 50566}, {"x": 183, "y": 45042}, {"x": 184, "y": 16180}, {"x": 185, "y": 66129}, {"x": 187, "y": 79029}, {"x": 190, "y": 30731}, {"x": 191, "y": 28990}, {"x": 192, "y": 7713}, {"x": 193, "y": 85833}, {"x": 194, "y": 61871}, {"x": 196, "y": 27675}, {"x": 197, "y": 50127}, {"x": 199, "y": 83701}, {"x": 200, "y": 51243}, {"x": 201, "y": 37108}, {"x": 204, "y": 49924}, {"x": 206, "y": 1657}, {"x": 208, "y": 17553}, {"x": 210, "y": 93596}, {"x": 211, "y": 62565}, {"x": 213, "y": 85815}, {"x": 214, "y": 29790}, {"x": 215, "y": 54630}, {"x": 217, "y": 52048}, {"x": 218, "y": 23270}, {"x": 219, "y": 24034}, {"x": 221, "y": 33884}, {"x": 222, "y": 35276}, {"x": 223, "y": 69358}, {"x": 224, "y": 10278}, {"x": 228, "y": 17850}, {"x": 229, "y": 52471}, {"x": 230, "y": 47271}, {"x": 232, "y": 74226}, {"x": 235, "y": 15651}, {"x": 236, "y": 7183}, {"x": 239, "y": 66253}, {"x": 243, "y": 49217}, {"x": 248, "y": 31689}, {"x": 251, "y": 67169}, {"x": 252, "y": 87702}, {"x": 253, "y": 29595}, {"x": 255, "y": 42224}, {"x": 257, "y": 75208}, {"x": 258, "y": 65116}, {"x": 259, "y": 23305}, {"x": 263, "y": 15699}, {"x": 266, "y": 22017}, {"x": 270, "y": 11118}, {"x": 276, "y": 68300}, {"x": 277, "y": 48894}, {"x": 283, "y": 82196}, {"x": 287, "y": 11109}, {"x": 290, "y": 37031}, {"x": 292, "y": 49042}, {"x": 294, "y": 80006}, {"x": 296, "y": 72757}, {"x": 298, "y": 70295}, {"x": 302, "y": 6426}, {"x": 304, "y": 56509}, {"x": 308, "y": 21990}, {"x": 310, "y": 70353}, {"x": 313, "y": 94088}, {"x": 314, "y": 95000}, {"x": 317, "y": 90160}, {"x": 319, "y": 2037}, {"x": 324, "y": 23909}, {"x": 327, "y": 76828}, {"x": 330, "y": 8779}, {"x": 334, "y": 80666}, {"x": 337, "y": 71923}, {"x": 341, "y": 65645}, {"x": 346, "y": 40166}, {"x": 348, "y": 42656}, {"x": 352, "y": 58022}, {"x": 358, "y": 71724}, {"x": 362, "y": 48295}, {"x": 368, "y": 79505}, {"x": 370, "y": 70684}, {"x": 380, "y": 22575}, {"x": 385, "y": 81205}, {"x": 391, "y": 24771}, {"x": 393, "y": 43827}, {"x": 397, "y": 35979}, {"x": 399, "y": 22881}, {"x": 412, "y": 25449}, {"x": 416, "y": 72494}, {"x": 424, "y": 6733}, {"x": 434, "y": 44334}, {"x": 440, "y": 48732}, {"x": 447, "y": 49335}, {"x": 456, "y": 72922}, {"x": 466, "y": 29807}, {"x": 470, "y": 97586}, {"x": 477, "y": 57187}, {"x": 486, "y": 99954}, {"x": 492, "y": 92827}, {"x": 505, "y": 31829}, {"x": 521, "y": 42697}, {"x": 532, "y": 18695}, {"x": 545, "y": 24815}, {"x": 553, "y": 39778}, {"x": 564, "y": 25776}, {"x": 583, "y": 83728}, {"x": 596, "y": 16837}, {"x": 612, "y": 62346}, {"x": 628, "y": 24415}, {"x": 657, "y": 83039}, {"x": 674, "y": 6333}, {"x": 693, "y": 18381}, {"x": 718, "y": 51107}, {"x": 738, "y": 87998}, {"x": 763, "y": 39015}, {"x": 787, "y": 95976}, {"x": 808, "y": 23891}, {"x": 836, "y": 54405}, {"x": 869, "y": 89033}, {"x": 903, "y": 7481}, {"x": 950, "y": 53549}, {"x": 987, "y": 21981}, {"x": 1050, "y": 41871}, {"x": 1104, "y": 54139}, {"x": 1163, "y": 3410}, {"x": 1233, "y": 45024}, {"x": 1317, "y": 87192}, {"x": 1442, "y": 9137}, {"x": 1581, "y": 34753}, {"x": 1720, "y": 99255}, {"x": 1939, "y": 37953}, {"x": 2203, "y": 46621}, {"x": 2515, "y": 75518}, {"x": 2962, "y": 48738}, {"x": 3698, "y": 23568}, {"x": 4619, "y": 9138}, {"x": 6234, "y": 44953}, {"x": 8898, "y": 52921}, {"x": 15184, "y": 15078}, {"x": 31478, "y": 22948}, {"x": 105142, "y": 85271}, {"x": 1014297, "y": 81223}]}