{"0": [{"x": 1, "y": 967}, {"x": 2, "y": 582}, {"x": 3, "y": 545}, {"x": 4, "y": 525}, {"x": 5, "y": 452}, {"x": 6, "y": 306}, {"x": 7, "y": 302}, {"x": 8, "y": 288}, {"x": 9, "y": 274}, {"x": 10, "y": 241}, {"x": 11, "y": 212}, {"x": 12, "y": 211}, {"x": 13, "y": 200}, {"x": 14, "y": 181}, {"x": 15, "y": 167}, {"x": 16, "y": 157}, {"x": 17, "y": 139}, {"x": 18, "y": 134}, {"x": 20, "y": 133}, {"x": 21, "y": 130}, {"x": 22, "y": 128}, {"x": 23, "y": 120}, {"x": 24, "y": 115}, {"x": 26, "y": 103}, {"x": 27, "y": 102}, {"x": 28, "y": 101}, {"x": 29, "y": 100}, {"x": 30, "y": 96}, {"x": 31, "y": 93}, {"x": 32, "y": 92}, {"x": 33, "y": 90}, {"x": 36, "y": 88}, {"x": 40, "y": 86}, {"x": 41, "y": 76}, {"x": 42, "y": 75}, {"x": 43, "y": 73}, {"x": 44, "y": 70}, {"x": 46, "y": 69}, {"x": 47, "y": 68}, {"x": 48, "y": 67}, {"x": 49, "y": 66}, {"x": 50, "y": 64}, {"x": 52, "y": 60}, {"x": 54, "y": 58}, {"x": 55, "y": 57}, {"x": 56, "y": 56}, {"x": 59, "y": 55}, {"x": 61, "y": 54}, {"x": 62, "y": 53}, {"x": 63, "y": 52}, {"x": 64, "y": 50}, {"x": 66, "y": 49}, {"x": 68, "y": 48}, {"x": 70, "y": 45}, {"x": 73, "y": 44}, {"x": 76, "y": 43}, {"x": 77, "y": 42}, {"x": 84, "y": 41}, {"x": 89, "y": 40}, {"x": 94, "y": 39}, {"x": 97, "y": 38}, {"x": 99, "y": 37}, {"x": 105, "y": 36}, {"x": 108, "y": 35}, {"x": 113, "y": 34}, {"x": 119, "y": 33}, {"x": 126, "y": 32}, {"x": 132, "y": 31}, {"x": 138, "y": 30}, {"x": 141, "y": 29}, {"x": 153, "y": 28}, {"x": 165, "y": 27}, {"x": 174, "y": 26}, {"x": 184, "y": 25}, {"x": 191, "y": 24}, {"x": 202, "y": 23}, {"x": 216, "y": 22}, {"x": 239, "y": 21}, {"x": 255, "y": 20}, {"x": 284, "y": 19}, {"x": 304, "y": 18}, {"x": 329, "y": 17}, {"x": 368, "y": 16}, {"x": 414, "y": 15}, {"x": 449, "y": 14}, {"x": 511, "y": 13}, {"x": 584, "y": 12}, {"x": 691, "y": 11}, {"x": 819, "y": 10}, {"x": 1005, "y": 9}, {"x": 1235, "y": 8}, {"x": 1617, "y": 7}, {"x": 2152, "y": 6}, {"x": 3114, "y": 5}, {"x": 4909, "y": 4}, {"x": 9124, "y": 3}, {"x": 20590, "y": 2}, {"x": 57504, "y": 1}], "1": [{"x": 57505, "y": 1096}, {"x": 57506, "y": 827}, {"x": 57507, "y": 645}, {"x": 57508, "y": 509}, {"x": 57509, "y": 413}, {"x": 57510, "y": 401}, {"x": 57511, "y": 397}, {"x": 57512, "y": 393}, {"x": 57513, "y": 350}, {"x": 57514, "y": 339}, {"x": 57515, "y": 299}, {"x": 57516, "y": 293}, {"x": 57517, "y": 241}, {"x": 57518, "y": 238}, {"x": 57519, "y": 220}, {"x": 57520, "y": 219}, {"x": 57521, "y": 216}, {"x": 57522, "y": 212}, {"x": 57523, "y": 200}, {"x": 57524, "y": 186}, {"x": 57525, "y": 183}, {"x": 57526, "y": 175}, {"x": 57527, "y": 166}, {"x": 57528, "y": 164}, {"x": 57529, "y": 161}, {"x": 57530, "y": 156}, {"x": 57531, "y": 154}, {"x": 57532, "y": 151}, {"x": 57533, "y": 149}, {"x": 57535, "y": 148}, {"x": 57537, "y": 146}, {"x": 57538, "y": 145}, {"x": 57539, "y": 135}, {"x": 57540, "y": 131}, {"x": 57541, "y": 129}, {"x": 57542, "y": 125}, {"x": 57543, "y": 116}, {"x": 57544, "y": 114}, {"x": 57545, "y": 111}, {"x": 57548, "y": 106}, {"x": 57550, "y": 98}, {"x": 57551, "y": 96}, {"x": 57553, "y": 95}, {"x": 57554, "y": 94}, {"x": 57555, "y": 87}, {"x": 57556, "y": 86}, {"x": 57557, "y": 81}, {"x": 57558, "y": 80}, {"x": 57559, "y": 79}, {"x": 57560, "y": 77}, {"x": 57563, "y": 74}, {"x": 57564, "y": 72}, {"x": 57566, "y": 69}, {"x": 57567, "y": 68}, {"x": 57568, "y": 67}, {"x": 57569, "y": 66}, {"x": 57571, "y": 65}, {"x": 57573, "y": 64}, {"x": 57575, "y": 63}, {"x": 57576, "y": 62}, {"x": 57578, "y": 61}, {"x": 57579, "y": 60}, {"x": 57584, "y": 59}, {"x": 57585, "y": 57}, {"x": 57588, "y": 55}, {"x": 57594, "y": 54}, {"x": 57595, "y": 53}, {"x": 57598, "y": 52}, {"x": 57602, "y": 51}, {"x": 57605, "y": 50}, {"x": 57611, "y": 48}, {"x": 57615, "y": 47}, {"x": 57617, "y": 46}, {"x": 57622, "y": 45}, {"x": 57625, "y": 44}, {"x": 57631, "y": 43}, {"x": 57633, "y": 42}, {"x": 57636, "y": 41}, {"x": 57641, "y": 40}, {"x": 57646, "y": 39}, {"x": 57652, "y": 38}, {"x": 57657, "y": 37}, {"x": 57661, "y": 36}, {"x": 57670, "y": 35}, {"x": 57674, "y": 34}, {"x": 57679, "y": 33}, {"x": 57693, "y": 32}, {"x": 57699, "y": 31}, {"x": 57707, "y": 30}, {"x": 57711, "y": 29}, {"x": 57724, "y": 28}, {"x": 57739, "y": 27}, {"x": 57753, "y": 26}, {"x": 57762, "y": 25}, {"x": 57771, "y": 24}, {"x": 57781, "y": 23}, {"x": 57795, "y": 22}, {"x": 57817, "y": 21}, {"x": 57840, "y": 20}, {"x": 57865, "y": 19}, {"x": 57900, "y": 18}, {"x": 57933, "y": 17}, {"x": 57964, "y": 16}, {"x": 58011, "y": 15}, {"x": 58062, "y": 14}, {"x": 58132, "y": 13}, {"x": 58221, "y": 12}, {"x": 58328, "y": 11}, {"x": 58473, "y": 10}, {"x": 58656, "y": 9}, {"x": 58942, "y": 8}, {"x": 59337, "y": 7}, {"x": 59967, "y": 6}, {"x": 61023, "y": 5}, {"x": 63330, "y": 4}, {"x": 67707, "y": 3}, {"x": 79656, "y": 2}, {"x": 117519, "y": 1}], "2": [{"x": 117520, "y": 1224}, {"x": 117521, "y": 1110}, {"x": 117522, "y": 937}, {"x": 117523, "y": 546}, {"x": 117524, "y": 485}, {"x": 117525, "y": 371}, {"x": 117526, "y": 309}, {"x": 117527, "y": 301}, {"x": 117528, "y": 285}, {"x": 117529, "y": 281}, {"x": 117530, "y": 261}, {"x": 117531, "y": 256}, {"x": 117532, "y": 241}, {"x": 117533, "y": 235}, {"x": 117534, "y": 227}, {"x": 117535, "y": 219}, {"x": 117536, "y": 200}, {"x": 117538, "y": 198}, {"x": 117539, "y": 188}, {"x": 117540, "y": 185}, {"x": 117541, "y": 174}, {"x": 117543, "y": 168}, {"x": 117544, "y": 166}, {"x": 117546, "y": 155}, {"x": 117547, "y": 149}, {"x": 117548, "y": 147}, {"x": 117549, "y": 143}, {"x": 117550, "y": 141}, {"x": 117551, "y": 139}, {"x": 117552, "y": 131}, {"x": 117553, "y": 129}, {"x": 117556, "y": 128}, {"x": 117557, "y": 127}, {"x": 117558, "y": 122}, {"x": 117559, "y": 112}, {"x": 117561, "y": 111}, {"x": 117562, "y": 110}, {"x": 117563, "y": 109}, {"x": 117564, "y": 107}, {"x": 117565, "y": 106}, {"x": 117566, "y": 99}, {"x": 117567, "y": 93}, {"x": 117568, "y": 90}, {"x": 117569, "y": 88}, {"x": 117570, "y": 87}, {"x": 117572, "y": 86}, {"x": 117574, "y": 85}, {"x": 117575, "y": 83}, {"x": 117577, "y": 82}, {"x": 117578, "y": 79}, {"x": 117581, "y": 78}, {"x": 117582, "y": 77}, {"x": 117583, "y": 72}, {"x": 117586, "y": 71}, {"x": 117587, "y": 70}, {"x": 117590, "y": 68}, {"x": 117591, "y": 67}, {"x": 117592, "y": 66}, {"x": 117595, "y": 64}, {"x": 117596, "y": 63}, {"x": 117600, "y": 60}, {"x": 117601, "y": 59}, {"x": 117603, "y": 57}, {"x": 117607, "y": 56}, {"x": 117609, "y": 54}, {"x": 117611, "y": 53}, {"x": 117612, "y": 52}, {"x": 117616, "y": 51}, {"x": 117620, "y": 50}, {"x": 117624, "y": 49}, {"x": 117626, "y": 48}, {"x": 117628, "y": 47}, {"x": 117630, "y": 46}, {"x": 117631, "y": 45}, {"x": 117638, "y": 44}, {"x": 117640, "y": 43}, {"x": 117644, "y": 42}, {"x": 117647, "y": 41}, {"x": 117649, "y": 40}, {"x": 117658, "y": 39}, {"x": 117660, "y": 38}, {"x": 117666, "y": 37}, {"x": 117674, "y": 36}, {"x": 117679, "y": 35}, {"x": 117688, "y": 34}, {"x": 117691, "y": 33}, {"x": 117695, "y": 32}, {"x": 117705, "y": 31}, {"x": 117713, "y": 30}, {"x": 117725, "y": 29}, {"x": 117731, "y": 28}, {"x": 117735, "y": 27}, {"x": 117746, "y": 26}, {"x": 117759, "y": 25}, {"x": 117775, "y": 24}, {"x": 117787, "y": 23}, {"x": 117806, "y": 22}, {"x": 117825, "y": 21}, {"x": 117843, "y": 20}, {"x": 117867, "y": 19}, {"x": 117896, "y": 18}, {"x": 117925, "y": 17}, {"x": 117947, "y": 16}, {"x": 117991, "y": 15}, {"x": 118049, "y": 14}, {"x": 118107, "y": 13}, {"x": 118203, "y": 12}, {"x": 118328, "y": 11}, {"x": 118467, "y": 10}, {"x": 118678, "y": 9}, {"x": 118935, "y": 8}, {"x": 119363, "y": 7}, {"x": 119941, "y": 6}, {"x": 121053, "y": 5}, {"x": 123005, "y": 4}, {"x": 127256, "y": 3}, {"x": 139084, "y": 2}, {"x": 176538, "y": 1}], "3": [{"x": 176539, "y": 1124}, {"x": 176540, "y": 860}, {"x": 176541, "y": 615}, {"x": 176542, "y": 586}, {"x": 176543, "y": 415}, {"x": 176544, "y": 267}, {"x": 176545, "y": 265}, {"x": 176546, "y": 216}, {"x": 176548, "y": 213}, {"x": 176549, "y": 206}, {"x": 176550, "y": 204}, {"x": 176551, "y": 191}, {"x": 176552, "y": 183}, {"x": 176553, "y": 179}, {"x": 176554, "y": 178}, {"x": 176555, "y": 147}, {"x": 176556, "y": 146}, {"x": 176557, "y": 138}, {"x": 176558, "y": 132}, {"x": 176559, "y": 126}, {"x": 176560, "y": 114}, {"x": 176562, "y": 113}, {"x": 176563, "y": 104}, {"x": 176564, "y": 103}, {"x": 176565, "y": 98}, {"x": 176566, "y": 94}, {"x": 176567, "y": 91}, {"x": 176568, "y": 90}, {"x": 176569, "y": 89}, {"x": 176570, "y": 85}, {"x": 176572, "y": 83}, {"x": 176573, "y": 81}, {"x": 176574, "y": 78}, {"x": 176575, "y": 77}, {"x": 176576, "y": 76}, {"x": 176577, "y": 72}, {"x": 176579, "y": 70}, {"x": 176580, "y": 68}, {"x": 176581, "y": 67}, {"x": 176582, "y": 65}, {"x": 176586, "y": 64}, {"x": 176588, "y": 63}, {"x": 176592, "y": 61}, {"x": 176594, "y": 60}, {"x": 176595, "y": 59}, {"x": 176596, "y": 58}, {"x": 176597, "y": 56}, {"x": 176598, "y": 55}, {"x": 176601, "y": 53}, {"x": 176603, "y": 52}, {"x": 176605, "y": 51}, {"x": 176607, "y": 50}, {"x": 176610, "y": 49}, {"x": 176615, "y": 48}, {"x": 176616, "y": 47}, {"x": 176618, "y": 46}, {"x": 176622, "y": 45}, {"x": 176625, "y": 43}, {"x": 176627, "y": 42}, {"x": 176628, "y": 41}, {"x": 176629, "y": 39}, {"x": 176631, "y": 38}, {"x": 176634, "y": 37}, {"x": 176639, "y": 36}, {"x": 176642, "y": 35}, {"x": 176650, "y": 34}, {"x": 176655, "y": 33}, {"x": 176665, "y": 32}, {"x": 176669, "y": 31}, {"x": 176677, "y": 30}, {"x": 176682, "y": 29}, {"x": 176690, "y": 28}, {"x": 176693, "y": 27}, {"x": 176698, "y": 26}, {"x": 176704, "y": 25}, {"x": 176720, "y": 24}, {"x": 176728, "y": 23}, {"x": 176737, "y": 22}, {"x": 176755, "y": 21}, {"x": 176774, "y": 20}, {"x": 176794, "y": 19}, {"x": 176822, "y": 18}, {"x": 176836, "y": 17}, {"x": 176865, "y": 16}, {"x": 176907, "y": 15}, {"x": 176952, "y": 14}, {"x": 177014, "y": 13}, {"x": 177073, "y": 12}, {"x": 177174, "y": 11}, {"x": 177307, "y": 10}, {"x": 177469, "y": 9}, {"x": 177726, "y": 8}, {"x": 178036, "y": 7}, {"x": 178592, "y": 6}, {"x": 179560, "y": 5}, {"x": 181410, "y": 4}, {"x": 185499, "y": 3}, {"x": 196939, "y": 2}, {"x": 233106, "y": 1}], "4": [{"x": 233107, "y": 911}, {"x": 233108, "y": 661}, {"x": 233109, "y": 244}, {"x": 233110, "y": 239}, {"x": 233111, "y": 215}, {"x": 233112, "y": 202}, {"x": 233113, "y": 197}, {"x": 233114, "y": 183}, {"x": 233115, "y": 147}, {"x": 233116, "y": 124}, {"x": 233117, "y": 123}, {"x": 233118, "y": 120}, {"x": 233119, "y": 113}, {"x": 233121, "y": 109}, {"x": 233122, "y": 108}, {"x": 233123, "y": 100}, {"x": 233125, "y": 97}, {"x": 233126, "y": 91}, {"x": 233127, "y": 90}, {"x": 233128, "y": 78}, {"x": 233129, "y": 73}, {"x": 233130, "y": 72}, {"x": 233134, "y": 69}, {"x": 233135, "y": 68}, {"x": 233136, "y": 67}, {"x": 233138, "y": 66}, {"x": 233140, "y": 65}, {"x": 233141, "y": 61}, {"x": 233142, "y": 58}, {"x": 233143, "y": 57}, {"x": 233144, "y": 55}, {"x": 233145, "y": 53}, {"x": 233146, "y": 51}, {"x": 233147, "y": 49}, {"x": 233149, "y": 48}, {"x": 233150, "y": 47}, {"x": 233152, "y": 46}, {"x": 233153, "y": 45}, {"x": 233156, "y": 44}, {"x": 233157, "y": 43}, {"x": 233158, "y": 42}, {"x": 233159, "y": 40}, {"x": 233161, "y": 39}, {"x": 233162, "y": 38}, {"x": 233168, "y": 37}, {"x": 233170, "y": 36}, {"x": 233174, "y": 35}, {"x": 233178, "y": 34}, {"x": 233183, "y": 33}, {"x": 233184, "y": 32}, {"x": 233188, "y": 31}, {"x": 233195, "y": 30}, {"x": 233198, "y": 29}, {"x": 233205, "y": 28}, {"x": 233209, "y": 27}, {"x": 233216, "y": 26}, {"x": 233222, "y": 25}, {"x": 233228, "y": 24}, {"x": 233232, "y": 23}, {"x": 233237, "y": 22}, {"x": 233249, "y": 21}, {"x": 233264, "y": 20}, {"x": 233277, "y": 19}, {"x": 233291, "y": 18}, {"x": 233306, "y": 17}, {"x": 233331, "y": 16}, {"x": 233351, "y": 15}, {"x": 233388, "y": 14}, {"x": 233438, "y": 13}, {"x": 233492, "y": 12}, {"x": 233556, "y": 11}, {"x": 233665, "y": 10}, {"x": 233811, "y": 9}, {"x": 234034, "y": 8}, {"x": 234363, "y": 7}, {"x": 234891, "y": 6}, {"x": 235769, "y": 5}, {"x": 237493, "y": 4}, {"x": 241085, "y": 3}, {"x": 251719, "y": 2}, {"x": 286333, "y": 1}], "5": [{"x": 286334, "y": 900}, {"x": 286335, "y": 588}, {"x": 286336, "y": 402}, {"x": 286337, "y": 218}, {"x": 286338, "y": 205}, {"x": 286339, "y": 184}, {"x": 286341, "y": 157}, {"x": 286342, "y": 153}, {"x": 286343, "y": 148}, {"x": 286344, "y": 136}, {"x": 286345, "y": 121}, {"x": 286346, "y": 120}, {"x": 286348, "y": 118}, {"x": 286349, "y": 108}, {"x": 286350, "y": 103}, {"x": 286351, "y": 93}, {"x": 286352, "y": 83}, {"x": 286353, "y": 82}, {"x": 286354, "y": 77}, {"x": 286355, "y": 76}, {"x": 286356, "y": 72}, {"x": 286357, "y": 67}, {"x": 286358, "y": 65}, {"x": 286360, "y": 63}, {"x": 286361, "y": 61}, {"x": 286363, "y": 60}, {"x": 286364, "y": 59}, {"x": 286367, "y": 56}, {"x": 286369, "y": 55}, {"x": 286370, "y": 54}, {"x": 286371, "y": 53}, {"x": 286372, "y": 51}, {"x": 286373, "y": 48}, {"x": 286374, "y": 44}, {"x": 286375, "y": 43}, {"x": 286379, "y": 42}, {"x": 286381, "y": 40}, {"x": 286383, "y": 39}, {"x": 286385, "y": 38}, {"x": 286387, "y": 37}, {"x": 286388, "y": 36}, {"x": 286390, "y": 35}, {"x": 286391, "y": 34}, {"x": 286392, "y": 33}, {"x": 286394, "y": 32}, {"x": 286400, "y": 31}, {"x": 286405, "y": 30}, {"x": 286408, "y": 29}, {"x": 286411, "y": 28}, {"x": 286414, "y": 27}, {"x": 286420, "y": 26}, {"x": 286424, "y": 25}, {"x": 286431, "y": 24}, {"x": 286438, "y": 23}, {"x": 286443, "y": 22}, {"x": 286445, "y": 21}, {"x": 286452, "y": 20}, {"x": 286470, "y": 19}, {"x": 286481, "y": 18}, {"x": 286494, "y": 17}, {"x": 286514, "y": 16}, {"x": 286536, "y": 15}, {"x": 286559, "y": 14}, {"x": 286592, "y": 13}, {"x": 286638, "y": 12}, {"x": 286698, "y": 11}, {"x": 286781, "y": 10}, {"x": 286883, "y": 9}, {"x": 287064, "y": 8}, {"x": 287308, "y": 7}, {"x": 287719, "y": 6}, {"x": 288497, "y": 5}, {"x": 289945, "y": 4}, {"x": 293414, "y": 3}, {"x": 303168, "y": 2}, {"x": 335535, "y": 1}], "6": [{"x": 335536, "y": 920}, {"x": 335537, "y": 884}, {"x": 335538, "y": 550}, {"x": 335539, "y": 497}, {"x": 335540, "y": 422}, {"x": 335541, "y": 237}, {"x": 335542, "y": 205}, {"x": 335543, "y": 189}, {"x": 335544, "y": 180}, {"x": 335545, "y": 177}, {"x": 335546, "y": 159}, {"x": 335547, "y": 149}, {"x": 335548, "y": 142}, {"x": 335549, "y": 141}, {"x": 335550, "y": 110}, {"x": 335551, "y": 104}, {"x": 335552, "y": 103}, {"x": 335553, "y": 95}, {"x": 335554, "y": 91}, {"x": 335555, "y": 82}, {"x": 335556, "y": 75}, {"x": 335557, "y": 72}, {"x": 335558, "y": 71}, {"x": 335559, "y": 70}, {"x": 335560, "y": 66}, {"x": 335561, "y": 64}, {"x": 335562, "y": 62}, {"x": 335563, "y": 61}, {"x": 335564, "y": 56}, {"x": 335565, "y": 55}, {"x": 335566, "y": 52}, {"x": 335567, "y": 51}, {"x": 335568, "y": 49}, {"x": 335570, "y": 47}, {"x": 335571, "y": 46}, {"x": 335573, "y": 45}, {"x": 335575, "y": 44}, {"x": 335577, "y": 41}, {"x": 335578, "y": 39}, {"x": 335579, "y": 38}, {"x": 335585, "y": 37}, {"x": 335588, "y": 36}, {"x": 335590, "y": 34}, {"x": 335591, "y": 33}, {"x": 335594, "y": 32}, {"x": 335596, "y": 31}, {"x": 335600, "y": 30}, {"x": 335606, "y": 29}, {"x": 335610, "y": 28}, {"x": 335619, "y": 26}, {"x": 335622, "y": 25}, {"x": 335628, "y": 24}, {"x": 335630, "y": 23}, {"x": 335635, "y": 22}, {"x": 335641, "y": 21}, {"x": 335652, "y": 20}, {"x": 335661, "y": 19}, {"x": 335678, "y": 18}, {"x": 335687, "y": 17}, {"x": 335708, "y": 16}, {"x": 335725, "y": 15}, {"x": 335750, "y": 14}, {"x": 335779, "y": 13}, {"x": 335814, "y": 12}, {"x": 335873, "y": 11}, {"x": 335934, "y": 10}, {"x": 336029, "y": 9}, {"x": 336179, "y": 8}, {"x": 336408, "y": 7}, {"x": 336784, "y": 6}, {"x": 337445, "y": 5}, {"x": 338829, "y": 4}, {"x": 341866, "y": 3}, {"x": 351153, "y": 2}, {"x": 381991, "y": 1}], "7": [{"x": 381992, "y": 809}, {"x": 381993, "y": 502}, {"x": 381994, "y": 385}, {"x": 381995, "y": 280}, {"x": 381997, "y": 174}, {"x": 381998, "y": 158}, {"x": 382000, "y": 153}, {"x": 382001, "y": 148}, {"x": 382002, "y": 133}, {"x": 382003, "y": 131}, {"x": 382004, "y": 109}, {"x": 382005, "y": 102}, {"x": 382006, "y": 93}, {"x": 382007, "y": 90}, {"x": 382009, "y": 77}, {"x": 382010, "y": 74}, {"x": 382011, "y": 71}, {"x": 382012, "y": 66}, {"x": 382013, "y": 62}, {"x": 382015, "y": 60}, {"x": 382016, "y": 58}, {"x": 382017, "y": 56}, {"x": 382018, "y": 52}, {"x": 382020, "y": 51}, {"x": 382021, "y": 50}, {"x": 382023, "y": 48}, {"x": 382024, "y": 44}, {"x": 382026, "y": 42}, {"x": 382027, "y": 40}, {"x": 382028, "y": 39}, {"x": 382029, "y": 37}, {"x": 382031, "y": 36}, {"x": 382032, "y": 35}, {"x": 382033, "y": 34}, {"x": 382036, "y": 33}, {"x": 382039, "y": 32}, {"x": 382040, "y": 31}, {"x": 382041, "y": 30}, {"x": 382045, "y": 28}, {"x": 382048, "y": 27}, {"x": 382049, "y": 26}, {"x": 382052, "y": 25}, {"x": 382056, "y": 24}, {"x": 382063, "y": 23}, {"x": 382069, "y": 22}, {"x": 382071, "y": 21}, {"x": 382079, "y": 20}, {"x": 382089, "y": 19}, {"x": 382102, "y": 18}, {"x": 382113, "y": 17}, {"x": 382125, "y": 16}, {"x": 382145, "y": 15}, {"x": 382163, "y": 14}, {"x": 382188, "y": 13}, {"x": 382218, "y": 12}, {"x": 382251, "y": 11}, {"x": 382302, "y": 10}, {"x": 382379, "y": 9}, {"x": 382497, "y": 8}, {"x": 382689, "y": 7}, {"x": 382983, "y": 6}, {"x": 383550, "y": 5}, {"x": 384732, "y": 4}, {"x": 387533, "y": 3}, {"x": 395781, "y": 2}, {"x": 424471, "y": 1}], "8": [{"x": 424472, "y": 777}, {"x": 424473, "y": 385}, {"x": 424474, "y": 373}, {"x": 424475, "y": 316}, {"x": 424476, "y": 194}, {"x": 424477, "y": 139}, {"x": 424478, "y": 134}, {"x": 424479, "y": 127}, {"x": 424480, "y": 122}, {"x": 424481, "y": 119}, {"x": 424482, "y": 113}, {"x": 424483, "y": 96}, {"x": 424485, "y": 81}, {"x": 424486, "y": 69}, {"x": 424488, "y": 64}, {"x": 424489, "y": 62}, {"x": 424491, "y": 56}, {"x": 424492, "y": 55}, {"x": 424493, "y": 52}, {"x": 424494, "y": 51}, {"x": 424495, "y": 48}, {"x": 424496, "y": 45}, {"x": 424497, "y": 43}, {"x": 424499, "y": 42}, {"x": 424500, "y": 40}, {"x": 424503, "y": 39}, {"x": 424504, "y": 38}, {"x": 424505, "y": 37}, {"x": 424506, "y": 36}, {"x": 424507, "y": 35}, {"x": 424509, "y": 33}, {"x": 424510, "y": 32}, {"x": 424514, "y": 31}, {"x": 424517, "y": 30}, {"x": 424518, "y": 29}, {"x": 424519, "y": 28}, {"x": 424520, "y": 27}, {"x": 424524, "y": 26}, {"x": 424525, "y": 25}, {"x": 424526, "y": 24}, {"x": 424528, "y": 23}, {"x": 424532, "y": 22}, {"x": 424540, "y": 21}, {"x": 424544, "y": 20}, {"x": 424549, "y": 19}, {"x": 424561, "y": 18}, {"x": 424570, "y": 17}, {"x": 424586, "y": 16}, {"x": 424599, "y": 15}, {"x": 424611, "y": 14}, {"x": 424637, "y": 13}, {"x": 424672, "y": 12}, {"x": 424701, "y": 11}, {"x": 424753, "y": 10}, {"x": 424820, "y": 9}, {"x": 424946, "y": 8}, {"x": 425119, "y": 7}, {"x": 425435, "y": 6}, {"x": 425997, "y": 5}, {"x": 427062, "y": 4}, {"x": 429712, "y": 3}, {"x": 437596, "y": 2}, {"x": 465007, "y": 1}], "9": [{"x": 465008, "y": 802}, {"x": 465009, "y": 321}, {"x": 465010, "y": 273}, {"x": 465011, "y": 191}, {"x": 465012, "y": 180}, {"x": 465013, "y": 154}, {"x": 465014, "y": 119}, {"x": 465015, "y": 115}, {"x": 465017, "y": 103}, {"x": 465018, "y": 101}, {"x": 465019, "y": 78}, {"x": 465020, "y": 75}, {"x": 465021, "y": 74}, {"x": 465022, "y": 71}, {"x": 465023, "y": 63}, {"x": 465025, "y": 62}, {"x": 465026, "y": 58}, {"x": 465029, "y": 55}, {"x": 465030, "y": 52}, {"x": 465031, "y": 50}, {"x": 465033, "y": 49}, {"x": 465035, "y": 48}, {"x": 465036, "y": 46}, {"x": 465037, "y": 44}, {"x": 465039, "y": 43}, {"x": 465040, "y": 39}, {"x": 465041, "y": 38}, {"x": 465043, "y": 37}, {"x": 465044, "y": 35}, {"x": 465046, "y": 32}, {"x": 465047, "y": 31}, {"x": 465049, "y": 30}, {"x": 465050, "y": 29}, {"x": 465052, "y": 28}, {"x": 465054, "y": 27}, {"x": 465057, "y": 26}, {"x": 465061, "y": 25}, {"x": 465066, "y": 24}, {"x": 465068, "y": 23}, {"x": 465077, "y": 22}, {"x": 465079, "y": 21}, {"x": 465089, "y": 20}, {"x": 465102, "y": 19}, {"x": 465113, "y": 18}, {"x": 465117, "y": 17}, {"x": 465125, "y": 16}, {"x": 465137, "y": 15}, {"x": 465162, "y": 14}, {"x": 465189, "y": 13}, {"x": 465214, "y": 12}, {"x": 465255, "y": 11}, {"x": 465306, "y": 10}, {"x": 465385, "y": 9}, {"x": 465475, "y": 8}, {"x": 465661, "y": 7}, {"x": 465939, "y": 6}, {"x": 466456, "y": 5}, {"x": 467538, "y": 4}, {"x": 470268, "y": 3}, {"x": 478251, "y": 2}, {"x": 506161, "y": 1}], "10": [{"x": 506162, "y": 869}, {"x": 506163, "y": 396}, {"x": 506164, "y": 349}, {"x": 506165, "y": 348}, {"x": 506166, "y": 293}, {"x": 506167, "y": 272}, {"x": 506168, "y": 259}, {"x": 506169, "y": 249}, {"x": 506170, "y": 182}, {"x": 506171, "y": 135}, {"x": 506172, "y": 134}, {"x": 506173, "y": 131}, {"x": 506174, "y": 115}, {"x": 506175, "y": 100}, {"x": 506176, "y": 89}, {"x": 506177, "y": 86}, {"x": 506178, "y": 85}, {"x": 506179, "y": 81}, {"x": 506180, "y": 79}, {"x": 506181, "y": 75}, {"x": 506182, "y": 74}, {"x": 506183, "y": 73}, {"x": 506184, "y": 71}, {"x": 506185, "y": 70}, {"x": 506186, "y": 68}, {"x": 506187, "y": 66}, {"x": 506189, "y": 63}, {"x": 506190, "y": 59}, {"x": 506191, "y": 58}, {"x": 506193, "y": 55}, {"x": 506194, "y": 52}, {"x": 506195, "y": 51}, {"x": 506196, "y": 48}, {"x": 506198, "y": 46}, {"x": 506199, "y": 45}, {"x": 506201, "y": 43}, {"x": 506203, "y": 42}, {"x": 506206, "y": 39}, {"x": 506208, "y": 37}, {"x": 506209, "y": 36}, {"x": 506212, "y": 35}, {"x": 506215, "y": 34}, {"x": 506217, "y": 33}, {"x": 506219, "y": 32}, {"x": 506221, "y": 31}, {"x": 506222, "y": 30}, {"x": 506224, "y": 29}, {"x": 506228, "y": 28}, {"x": 506231, "y": 27}, {"x": 506234, "y": 26}, {"x": 506236, "y": 25}, {"x": 506239, "y": 24}, {"x": 506243, "y": 23}, {"x": 506248, "y": 22}, {"x": 506253, "y": 21}, {"x": 506262, "y": 20}, {"x": 506270, "y": 19}, {"x": 506282, "y": 18}, {"x": 506288, "y": 17}, {"x": 506304, "y": 16}, {"x": 506324, "y": 15}, {"x": 506354, "y": 14}, {"x": 506389, "y": 13}, {"x": 506428, "y": 12}, {"x": 506467, "y": 11}, {"x": 506537, "y": 10}, {"x": 506630, "y": 9}, {"x": 506767, "y": 8}, {"x": 506975, "y": 7}, {"x": 507305, "y": 6}, {"x": 507912, "y": 5}, {"x": 509144, "y": 4}, {"x": 512041, "y": 3}, {"x": 520597, "y": 2}, {"x": 550529, "y": 1}], "11": [{"x": 550530, "y": 865}, {"x": 550531, "y": 534}, {"x": 550532, "y": 433}, {"x": 550533, "y": 357}, {"x": 550534, "y": 349}, {"x": 550535, "y": 236}, {"x": 550536, "y": 206}, {"x": 550537, "y": 178}, {"x": 550538, "y": 173}, {"x": 550539, "y": 144}, {"x": 550540, "y": 138}, {"x": 550541, "y": 114}, {"x": 550542, "y": 113}, {"x": 550543, "y": 111}, {"x": 550544, "y": 102}, {"x": 550545, "y": 89}, {"x": 550546, "y": 88}, {"x": 550547, "y": 85}, {"x": 550550, "y": 84}, {"x": 550551, "y": 79}, {"x": 550552, "y": 77}, {"x": 550554, "y": 72}, {"x": 550555, "y": 63}, {"x": 550556, "y": 61}, {"x": 550558, "y": 59}, {"x": 550559, "y": 57}, {"x": 550560, "y": 53}, {"x": 550561, "y": 51}, {"x": 550562, "y": 50}, {"x": 550563, "y": 49}, {"x": 550565, "y": 48}, {"x": 550566, "y": 47}, {"x": 550567, "y": 44}, {"x": 550568, "y": 43}, {"x": 550569, "y": 42}, {"x": 550570, "y": 40}, {"x": 550573, "y": 39}, {"x": 550574, "y": 36}, {"x": 550575, "y": 35}, {"x": 550578, "y": 34}, {"x": 550580, "y": 33}, {"x": 550584, "y": 32}, {"x": 550587, "y": 31}, {"x": 550588, "y": 30}, {"x": 550589, "y": 29}, {"x": 550594, "y": 28}, {"x": 550596, "y": 27}, {"x": 550599, "y": 26}, {"x": 550604, "y": 25}, {"x": 550608, "y": 24}, {"x": 550616, "y": 23}, {"x": 550623, "y": 22}, {"x": 550629, "y": 21}, {"x": 550641, "y": 20}, {"x": 550653, "y": 19}, {"x": 550667, "y": 18}, {"x": 550681, "y": 17}, {"x": 550693, "y": 16}, {"x": 550714, "y": 15}, {"x": 550746, "y": 14}, {"x": 550778, "y": 13}, {"x": 550815, "y": 12}, {"x": 550868, "y": 11}, {"x": 550937, "y": 10}, {"x": 551044, "y": 9}, {"x": 551218, "y": 8}, {"x": 551453, "y": 7}, {"x": 551820, "y": 6}, {"x": 552502, "y": 5}, {"x": 553801, "y": 4}, {"x": 556989, "y": 3}, {"x": 566444, "y": 2}, {"x": 598392, "y": 1}], "12": [{"x": 598393, "y": 980}, {"x": 598394, "y": 686}, {"x": 598395, "y": 471}, {"x": 598396, "y": 423}, {"x": 598397, "y": 305}, {"x": 598398, "y": 253}, {"x": 598399, "y": 240}, {"x": 598400, "y": 220}, {"x": 598401, "y": 197}, {"x": 598402, "y": 196}, {"x": 598403, "y": 184}, {"x": 598404, "y": 168}, {"x": 598405, "y": 157}, {"x": 598406, "y": 135}, {"x": 598407, "y": 122}, {"x": 598408, "y": 119}, {"x": 598409, "y": 116}, {"x": 598410, "y": 106}, {"x": 598411, "y": 92}, {"x": 598412, "y": 91}, {"x": 598413, "y": 86}, {"x": 598414, "y": 85}, {"x": 598416, "y": 83}, {"x": 598417, "y": 78}, {"x": 598419, "y": 74}, {"x": 598420, "y": 73}, {"x": 598421, "y": 69}, {"x": 598422, "y": 68}, {"x": 598423, "y": 65}, {"x": 598424, "y": 64}, {"x": 598425, "y": 63}, {"x": 598426, "y": 61}, {"x": 598427, "y": 60}, {"x": 598428, "y": 56}, {"x": 598430, "y": 52}, {"x": 598431, "y": 48}, {"x": 598433, "y": 47}, {"x": 598436, "y": 43}, {"x": 598438, "y": 41}, {"x": 598439, "y": 40}, {"x": 598440, "y": 39}, {"x": 598442, "y": 38}, {"x": 598443, "y": 37}, {"x": 598444, "y": 36}, {"x": 598448, "y": 35}, {"x": 598451, "y": 34}, {"x": 598452, "y": 33}, {"x": 598456, "y": 32}, {"x": 598458, "y": 31}, {"x": 598462, "y": 30}, {"x": 598465, "y": 29}, {"x": 598468, "y": 28}, {"x": 598474, "y": 27}, {"x": 598479, "y": 26}, {"x": 598485, "y": 25}, {"x": 598493, "y": 24}, {"x": 598499, "y": 23}, {"x": 598505, "y": 22}, {"x": 598513, "y": 21}, {"x": 598525, "y": 20}, {"x": 598537, "y": 19}, {"x": 598543, "y": 18}, {"x": 598558, "y": 17}, {"x": 598577, "y": 16}, {"x": 598600, "y": 15}, {"x": 598628, "y": 14}, {"x": 598658, "y": 13}, {"x": 598701, "y": 12}, {"x": 598758, "y": 11}, {"x": 598836, "y": 10}, {"x": 598948, "y": 9}, {"x": 599103, "y": 8}, {"x": 599331, "y": 7}, {"x": 599753, "y": 6}, {"x": 600501, "y": 5}, {"x": 601957, "y": 4}, {"x": 605365, "y": 3}, {"x": 615435, "y": 2}, {"x": 649578, "y": 1}], "13": [{"x": 649579, "y": 1424}, {"x": 649580, "y": 987}, {"x": 649581, "y": 721}, {"x": 649582, "y": 343}, {"x": 649583, "y": 273}, {"x": 649584, "y": 267}, {"x": 649585, "y": 243}, {"x": 649586, "y": 187}, {"x": 649587, "y": 182}, {"x": 649588, "y": 161}, {"x": 649589, "y": 160}, {"x": 649590, "y": 141}, {"x": 649591, "y": 124}, {"x": 649592, "y": 106}, {"x": 649593, "y": 101}, {"x": 649594, "y": 85}, {"x": 649595, "y": 83}, {"x": 649596, "y": 80}, {"x": 649597, "y": 79}, {"x": 649599, "y": 75}, {"x": 649600, "y": 74}, {"x": 649601, "y": 70}, {"x": 649603, "y": 68}, {"x": 649604, "y": 65}, {"x": 649605, "y": 64}, {"x": 649607, "y": 62}, {"x": 649609, "y": 59}, {"x": 649611, "y": 58}, {"x": 649612, "y": 54}, {"x": 649613, "y": 52}, {"x": 649614, "y": 47}, {"x": 649615, "y": 46}, {"x": 649616, "y": 45}, {"x": 649617, "y": 44}, {"x": 649621, "y": 43}, {"x": 649622, "y": 41}, {"x": 649624, "y": 40}, {"x": 649625, "y": 38}, {"x": 649627, "y": 37}, {"x": 649629, "y": 36}, {"x": 649630, "y": 35}, {"x": 649634, "y": 34}, {"x": 649638, "y": 33}, {"x": 649640, "y": 32}, {"x": 649643, "y": 31}, {"x": 649648, "y": 30}, {"x": 649651, "y": 29}, {"x": 649655, "y": 28}, {"x": 649657, "y": 27}, {"x": 649661, "y": 26}, {"x": 649672, "y": 25}, {"x": 649678, "y": 24}, {"x": 649686, "y": 23}, {"x": 649693, "y": 22}, {"x": 649697, "y": 21}, {"x": 649706, "y": 20}, {"x": 649716, "y": 19}, {"x": 649733, "y": 18}, {"x": 649747, "y": 17}, {"x": 649768, "y": 16}, {"x": 649795, "y": 15}, {"x": 649834, "y": 14}, {"x": 649869, "y": 13}, {"x": 649921, "y": 12}, {"x": 649980, "y": 11}, {"x": 650064, "y": 10}, {"x": 650192, "y": 9}, {"x": 650339, "y": 8}, {"x": 650610, "y": 7}, {"x": 651061, "y": 6}, {"x": 651863, "y": 5}, {"x": 653446, "y": 4}, {"x": 657255, "y": 3}, {"x": 667862, "y": 2}, {"x": 703989, "y": 1}], "14": [{"x": 703990, "y": 1811}, {"x": 703991, "y": 1064}, {"x": 703992, "y": 670}, {"x": 703993, "y": 539}, {"x": 703994, "y": 385}, {"x": 703995, "y": 300}, {"x": 703996, "y": 247}, {"x": 703997, "y": 217}, {"x": 703998, "y": 195}, {"x": 703999, "y": 173}, {"x": 704000, "y": 164}, {"x": 704001, "y": 141}, {"x": 704002, "y": 135}, {"x": 704003, "y": 121}, {"x": 704005, "y": 108}, {"x": 704006, "y": 106}, {"x": 704007, "y": 98}, {"x": 704008, "y": 96}, {"x": 704009, "y": 89}, {"x": 704010, "y": 86}, {"x": 704011, "y": 85}, {"x": 704012, "y": 82}, {"x": 704013, "y": 81}, {"x": 704014, "y": 77}, {"x": 704015, "y": 72}, {"x": 704016, "y": 70}, {"x": 704017, "y": 68}, {"x": 704018, "y": 67}, {"x": 704019, "y": 66}, {"x": 704020, "y": 62}, {"x": 704021, "y": 61}, {"x": 704023, "y": 55}, {"x": 704026, "y": 52}, {"x": 704027, "y": 51}, {"x": 704028, "y": 50}, {"x": 704029, "y": 46}, {"x": 704030, "y": 45}, {"x": 704031, "y": 44}, {"x": 704033, "y": 43}, {"x": 704036, "y": 41}, {"x": 704037, "y": 40}, {"x": 704038, "y": 39}, {"x": 704040, "y": 38}, {"x": 704041, "y": 37}, {"x": 704043, "y": 36}, {"x": 704045, "y": 35}, {"x": 704047, "y": 34}, {"x": 704050, "y": 32}, {"x": 704053, "y": 31}, {"x": 704055, "y": 30}, {"x": 704063, "y": 29}, {"x": 704068, "y": 28}, {"x": 704071, "y": 27}, {"x": 704074, "y": 26}, {"x": 704082, "y": 25}, {"x": 704087, "y": 24}, {"x": 704095, "y": 23}, {"x": 704103, "y": 22}, {"x": 704112, "y": 21}, {"x": 704125, "y": 20}, {"x": 704138, "y": 19}, {"x": 704146, "y": 18}, {"x": 704167, "y": 17}, {"x": 704192, "y": 16}, {"x": 704214, "y": 15}, {"x": 704249, "y": 14}, {"x": 704287, "y": 13}, {"x": 704334, "y": 12}, {"x": 704419, "y": 11}, {"x": 704505, "y": 10}, {"x": 704634, "y": 9}, {"x": 704834, "y": 8}, {"x": 705106, "y": 7}, {"x": 705613, "y": 6}, {"x": 706512, "y": 5}, {"x": 708158, "y": 4}, {"x": 712011, "y": 3}, {"x": 723203, "y": 2}, {"x": 760108, "y": 1}], "15": [{"x": 760109, "y": 1503}, {"x": 760110, "y": 995}, {"x": 760111, "y": 660}, {"x": 760112, "y": 390}, {"x": 760113, "y": 324}, {"x": 760114, "y": 261}, {"x": 760115, "y": 256}, {"x": 760116, "y": 227}, {"x": 760117, "y": 225}, {"x": 760118, "y": 163}, {"x": 760119, "y": 153}, {"x": 760120, "y": 142}, {"x": 760121, "y": 134}, {"x": 760122, "y": 126}, {"x": 760123, "y": 103}, {"x": 760124, "y": 100}, {"x": 760125, "y": 98}, {"x": 760126, "y": 95}, {"x": 760127, "y": 93}, {"x": 760128, "y": 91}, {"x": 760129, "y": 90}, {"x": 760130, "y": 85}, {"x": 760131, "y": 80}, {"x": 760132, "y": 78}, {"x": 760133, "y": 76}, {"x": 760135, "y": 71}, {"x": 760136, "y": 64}, {"x": 760138, "y": 62}, {"x": 760141, "y": 59}, {"x": 760142, "y": 58}, {"x": 760143, "y": 56}, {"x": 760144, "y": 54}, {"x": 760146, "y": 50}, {"x": 760147, "y": 49}, {"x": 760149, "y": 48}, {"x": 760150, "y": 47}, {"x": 760152, "y": 46}, {"x": 760153, "y": 44}, {"x": 760154, "y": 43}, {"x": 760156, "y": 42}, {"x": 760157, "y": 41}, {"x": 760159, "y": 40}, {"x": 760160, "y": 38}, {"x": 760162, "y": 37}, {"x": 760165, "y": 36}, {"x": 760167, "y": 35}, {"x": 760170, "y": 34}, {"x": 760171, "y": 33}, {"x": 760173, "y": 32}, {"x": 760177, "y": 30}, {"x": 760180, "y": 29}, {"x": 760184, "y": 28}, {"x": 760190, "y": 27}, {"x": 760196, "y": 26}, {"x": 760199, "y": 25}, {"x": 760207, "y": 24}, {"x": 760219, "y": 23}, {"x": 760229, "y": 22}, {"x": 760240, "y": 21}, {"x": 760255, "y": 20}, {"x": 760267, "y": 19}, {"x": 760283, "y": 18}, {"x": 760303, "y": 17}, {"x": 760326, "y": 16}, {"x": 760344, "y": 15}, {"x": 760380, "y": 14}, {"x": 760419, "y": 13}, {"x": 760468, "y": 12}, {"x": 760543, "y": 11}, {"x": 760650, "y": 10}, {"x": 760810, "y": 9}, {"x": 761004, "y": 8}, {"x": 761311, "y": 7}, {"x": 761830, "y": 6}, {"x": 762707, "y": 5}, {"x": 764449, "y": 4}, {"x": 768490, "y": 3}, {"x": 779912, "y": 2}, {"x": 817985, "y": 1}], "16": [{"x": 817986, "y": 1076}, {"x": 817987, "y": 604}, {"x": 817988, "y": 338}, {"x": 817989, "y": 300}, {"x": 817990, "y": 283}, {"x": 817991, "y": 240}, {"x": 817992, "y": 217}, {"x": 817993, "y": 199}, {"x": 817994, "y": 177}, {"x": 817995, "y": 162}, {"x": 817996, "y": 156}, {"x": 817997, "y": 146}, {"x": 817998, "y": 145}, {"x": 818000, "y": 136}, {"x": 818001, "y": 125}, {"x": 818002, "y": 120}, {"x": 818003, "y": 118}, {"x": 818004, "y": 112}, {"x": 818005, "y": 96}, {"x": 818006, "y": 87}, {"x": 818008, "y": 86}, {"x": 818009, "y": 83}, {"x": 818010, "y": 81}, {"x": 818013, "y": 80}, {"x": 818014, "y": 76}, {"x": 818015, "y": 75}, {"x": 818016, "y": 69}, {"x": 818017, "y": 68}, {"x": 818019, "y": 66}, {"x": 818020, "y": 64}, {"x": 818021, "y": 63}, {"x": 818022, "y": 56}, {"x": 818024, "y": 55}, {"x": 818027, "y": 54}, {"x": 818028, "y": 53}, {"x": 818030, "y": 52}, {"x": 818031, "y": 51}, {"x": 818033, "y": 50}, {"x": 818035, "y": 49}, {"x": 818037, "y": 48}, {"x": 818038, "y": 47}, {"x": 818040, "y": 46}, {"x": 818041, "y": 45}, {"x": 818043, "y": 44}, {"x": 818044, "y": 42}, {"x": 818047, "y": 41}, {"x": 818049, "y": 40}, {"x": 818052, "y": 39}, {"x": 818053, "y": 38}, {"x": 818054, "y": 37}, {"x": 818055, "y": 36}, {"x": 818057, "y": 35}, {"x": 818058, "y": 34}, {"x": 818061, "y": 33}, {"x": 818062, "y": 32}, {"x": 818066, "y": 31}, {"x": 818070, "y": 30}, {"x": 818077, "y": 29}, {"x": 818081, "y": 28}, {"x": 818083, "y": 27}, {"x": 818088, "y": 26}, {"x": 818095, "y": 25}, {"x": 818104, "y": 24}, {"x": 818110, "y": 23}, {"x": 818117, "y": 22}, {"x": 818133, "y": 21}, {"x": 818153, "y": 20}, {"x": 818165, "y": 19}, {"x": 818180, "y": 18}, {"x": 818206, "y": 17}, {"x": 818230, "y": 16}, {"x": 818270, "y": 15}, {"x": 818305, "y": 14}, {"x": 818347, "y": 13}, {"x": 818412, "y": 12}, {"x": 818488, "y": 11}, {"x": 818603, "y": 10}, {"x": 818758, "y": 9}, {"x": 818983, "y": 8}, {"x": 819333, "y": 7}, {"x": 819880, "y": 6}, {"x": 820863, "y": 5}, {"x": 822752, "y": 4}, {"x": 827031, "y": 3}, {"x": 839184, "y": 2}, {"x": 878637, "y": 1}], "17": [{"x": 878638, "y": 1072}, {"x": 878639, "y": 496}, {"x": 878640, "y": 490}, {"x": 878641, "y": 350}, {"x": 878642, "y": 345}, {"x": 878643, "y": 297}, {"x": 878644, "y": 252}, {"x": 878645, "y": 218}, {"x": 878646, "y": 213}, {"x": 878647, "y": 162}, {"x": 878648, "y": 154}, {"x": 878649, "y": 150}, {"x": 878650, "y": 147}, {"x": 878651, "y": 135}, {"x": 878652, "y": 125}, {"x": 878653, "y": 124}, {"x": 878654, "y": 120}, {"x": 878655, "y": 105}, {"x": 878656, "y": 96}, {"x": 878657, "y": 93}, {"x": 878658, "y": 87}, {"x": 878659, "y": 82}, {"x": 878660, "y": 81}, {"x": 878661, "y": 78}, {"x": 878663, "y": 77}, {"x": 878664, "y": 73}, {"x": 878665, "y": 72}, {"x": 878666, "y": 71}, {"x": 878667, "y": 68}, {"x": 878668, "y": 67}, {"x": 878669, "y": 65}, {"x": 878670, "y": 58}, {"x": 878671, "y": 56}, {"x": 878672, "y": 53}, {"x": 878674, "y": 52}, {"x": 878675, "y": 49}, {"x": 878678, "y": 46}, {"x": 878680, "y": 45}, {"x": 878685, "y": 43}, {"x": 878688, "y": 40}, {"x": 878690, "y": 39}, {"x": 878691, "y": 38}, {"x": 878692, "y": 37}, {"x": 878697, "y": 36}, {"x": 878703, "y": 35}, {"x": 878705, "y": 34}, {"x": 878713, "y": 33}, {"x": 878720, "y": 31}, {"x": 878724, "y": 29}, {"x": 878730, "y": 28}, {"x": 878736, "y": 27}, {"x": 878748, "y": 26}, {"x": 878755, "y": 25}, {"x": 878762, "y": 24}, {"x": 878772, "y": 23}, {"x": 878781, "y": 22}, {"x": 878792, "y": 21}, {"x": 878803, "y": 20}, {"x": 878819, "y": 19}, {"x": 878841, "y": 18}, {"x": 878863, "y": 17}, {"x": 878887, "y": 16}, {"x": 878917, "y": 15}, {"x": 878965, "y": 14}, {"x": 879019, "y": 13}, {"x": 879076, "y": 12}, {"x": 879154, "y": 11}, {"x": 879269, "y": 10}, {"x": 879436, "y": 9}, {"x": 879679, "y": 8}, {"x": 880029, "y": 7}, {"x": 880580, "y": 6}, {"x": 881527, "y": 5}, {"x": 883561, "y": 4}, {"x": 888021, "y": 3}, {"x": 900700, "y": 2}, {"x": 941303, "y": 1}], "18": [{"x": 941304, "y": 1143}, {"x": 941305, "y": 474}, {"x": 941306, "y": 418}, {"x": 941307, "y": 359}, {"x": 941309, "y": 265}, {"x": 941310, "y": 220}, {"x": 941311, "y": 202}, {"x": 941312, "y": 176}, {"x": 941313, "y": 167}, {"x": 941314, "y": 150}, {"x": 941315, "y": 127}, {"x": 941316, "y": 126}, {"x": 941317, "y": 115}, {"x": 941318, "y": 114}, {"x": 941319, "y": 113}, {"x": 941320, "y": 109}, {"x": 941321, "y": 108}, {"x": 941322, "y": 94}, {"x": 941323, "y": 93}, {"x": 941324, "y": 91}, {"x": 941327, "y": 89}, {"x": 941328, "y": 85}, {"x": 941329, "y": 82}, {"x": 941330, "y": 80}, {"x": 941331, "y": 79}, {"x": 941332, "y": 71}, {"x": 941333, "y": 66}, {"x": 941334, "y": 60}, {"x": 941335, "y": 59}, {"x": 941336, "y": 58}, {"x": 941337, "y": 57}, {"x": 941339, "y": 56}, {"x": 941340, "y": 54}, {"x": 941342, "y": 53}, {"x": 941344, "y": 52}, {"x": 941345, "y": 50}, {"x": 941347, "y": 49}, {"x": 941348, "y": 48}, {"x": 941352, "y": 47}, {"x": 941353, "y": 46}, {"x": 941355, "y": 45}, {"x": 941356, "y": 44}, {"x": 941357, "y": 43}, {"x": 941358, "y": 42}, {"x": 941362, "y": 41}, {"x": 941363, "y": 40}, {"x": 941366, "y": 39}, {"x": 941368, "y": 38}, {"x": 941370, "y": 37}, {"x": 941372, "y": 36}, {"x": 941379, "y": 35}, {"x": 941381, "y": 34}, {"x": 941385, "y": 33}, {"x": 941392, "y": 32}, {"x": 941394, "y": 31}, {"x": 941397, "y": 30}, {"x": 941403, "y": 29}, {"x": 941408, "y": 28}, {"x": 941412, "y": 27}, {"x": 941424, "y": 26}, {"x": 941432, "y": 25}, {"x": 941442, "y": 24}, {"x": 941448, "y": 23}, {"x": 941459, "y": 22}, {"x": 941471, "y": 21}, {"x": 941484, "y": 20}, {"x": 941511, "y": 19}, {"x": 941530, "y": 18}, {"x": 941557, "y": 17}, {"x": 941595, "y": 16}, {"x": 941636, "y": 15}, {"x": 941685, "y": 14}, {"x": 941751, "y": 13}, {"x": 941816, "y": 12}, {"x": 941905, "y": 11}, {"x": 942038, "y": 10}, {"x": 942209, "y": 9}, {"x": 942453, "y": 8}, {"x": 942866, "y": 7}, {"x": 943490, "y": 6}, {"x": 944482, "y": 5}, {"x": 946502, "y": 4}, {"x": 951100, "y": 3}, {"x": 963755, "y": 2}, {"x": 1005389, "y": 1}], "19": [{"x": 1005390, "y": 1019}, {"x": 1005391, "y": 760}, {"x": 1005392, "y": 648}, {"x": 1005393, "y": 521}, {"x": 1005394, "y": 433}, {"x": 1005395, "y": 419}, {"x": 1005396, "y": 312}, {"x": 1005397, "y": 287}, {"x": 1005398, "y": 256}, {"x": 1005399, "y": 211}, {"x": 1005400, "y": 191}, {"x": 1005401, "y": 187}, {"x": 1005402, "y": 175}, {"x": 1005403, "y": 162}, {"x": 1005404, "y": 160}, {"x": 1005405, "y": 159}, {"x": 1005406, "y": 141}, {"x": 1005407, "y": 134}, {"x": 1005408, "y": 116}, {"x": 1005409, "y": 111}, {"x": 1005410, "y": 107}, {"x": 1005411, "y": 101}, {"x": 1005413, "y": 89}, {"x": 1005414, "y": 88}, {"x": 1005415, "y": 83}, {"x": 1005416, "y": 76}, {"x": 1005417, "y": 73}, {"x": 1005420, "y": 71}, {"x": 1005422, "y": 70}, {"x": 1005423, "y": 69}, {"x": 1005424, "y": 67}, {"x": 1005426, "y": 63}, {"x": 1005427, "y": 62}, {"x": 1005428, "y": 61}, {"x": 1005429, "y": 60}, {"x": 1005430, "y": 59}, {"x": 1005431, "y": 58}, {"x": 1005432, "y": 57}, {"x": 1005433, "y": 54}, {"x": 1005434, "y": 53}, {"x": 1005436, "y": 51}, {"x": 1005437, "y": 50}, {"x": 1005439, "y": 49}, {"x": 1005440, "y": 48}, {"x": 1005444, "y": 46}, {"x": 1005445, "y": 45}, {"x": 1005447, "y": 43}, {"x": 1005449, "y": 41}, {"x": 1005450, "y": 40}, {"x": 1005452, "y": 39}, {"x": 1005454, "y": 38}, {"x": 1005456, "y": 37}, {"x": 1005461, "y": 36}, {"x": 1005469, "y": 35}, {"x": 1005474, "y": 34}, {"x": 1005481, "y": 33}, {"x": 1005486, "y": 32}, {"x": 1005488, "y": 31}, {"x": 1005494, "y": 30}, {"x": 1005500, "y": 29}, {"x": 1005506, "y": 28}, {"x": 1005518, "y": 27}, {"x": 1005523, "y": 26}, {"x": 1005535, "y": 25}, {"x": 1005544, "y": 24}, {"x": 1005555, "y": 23}, {"x": 1005572, "y": 22}, {"x": 1005583, "y": 21}, {"x": 1005606, "y": 20}, {"x": 1005625, "y": 19}, {"x": 1005648, "y": 18}, {"x": 1005675, "y": 17}, {"x": 1005709, "y": 16}, {"x": 1005751, "y": 15}, {"x": 1005811, "y": 14}, {"x": 1005867, "y": 13}, {"x": 1005948, "y": 12}, {"x": 1006053, "y": 11}, {"x": 1006191, "y": 10}, {"x": 1006402, "y": 9}, {"x": 1006667, "y": 8}, {"x": 1007084, "y": 7}, {"x": 1007764, "y": 6}, {"x": 1008886, "y": 5}, {"x": 1011025, "y": 4}, {"x": 1015788, "y": 3}, {"x": 1028807, "y": 2}, {"x": 1071165, "y": 1}], "20": [{"x": 1071166, "y": 997}, {"x": 1071167, "y": 883}, {"x": 1071168, "y": 465}, {"x": 1071169, "y": 416}, {"x": 1071170, "y": 394}, {"x": 1071171, "y": 393}, {"x": 1071172, "y": 357}, {"x": 1071173, "y": 345}, {"x": 1071174, "y": 342}, {"x": 1071175, "y": 334}, {"x": 1071176, "y": 320}, {"x": 1071177, "y": 313}, {"x": 1071178, "y": 272}, {"x": 1071179, "y": 252}, {"x": 1071180, "y": 233}, {"x": 1071181, "y": 228}, {"x": 1071182, "y": 202}, {"x": 1071183, "y": 200}, {"x": 1071184, "y": 182}, {"x": 1071185, "y": 176}, {"x": 1071186, "y": 163}, {"x": 1071187, "y": 160}, {"x": 1071188, "y": 157}, {"x": 1071189, "y": 137}, {"x": 1071190, "y": 136}, {"x": 1071191, "y": 131}, {"x": 1071192, "y": 121}, {"x": 1071193, "y": 106}, {"x": 1071194, "y": 104}, {"x": 1071195, "y": 100}, {"x": 1071196, "y": 99}, {"x": 1071197, "y": 98}, {"x": 1071198, "y": 94}, {"x": 1071199, "y": 93}, {"x": 1071200, "y": 90}, {"x": 1071201, "y": 89}, {"x": 1071203, "y": 87}, {"x": 1071205, "y": 84}, {"x": 1071206, "y": 83}, {"x": 1071207, "y": 82}, {"x": 1071208, "y": 81}, {"x": 1071209, "y": 80}, {"x": 1071210, "y": 74}, {"x": 1071211, "y": 73}, {"x": 1071212, "y": 70}, {"x": 1071214, "y": 68}, {"x": 1071215, "y": 63}, {"x": 1071218, "y": 61}, {"x": 1071219, "y": 58}, {"x": 1071221, "y": 56}, {"x": 1071223, "y": 55}, {"x": 1071224, "y": 53}, {"x": 1071225, "y": 52}, {"x": 1071226, "y": 51}, {"x": 1071229, "y": 50}, {"x": 1071230, "y": 48}, {"x": 1071231, "y": 47}, {"x": 1071233, "y": 46}, {"x": 1071235, "y": 45}, {"x": 1071237, "y": 44}, {"x": 1071240, "y": 43}, {"x": 1071243, "y": 41}, {"x": 1071245, "y": 40}, {"x": 1071247, "y": 39}, {"x": 1071253, "y": 38}, {"x": 1071257, "y": 37}, {"x": 1071259, "y": 36}, {"x": 1071262, "y": 35}, {"x": 1071265, "y": 34}, {"x": 1071269, "y": 33}, {"x": 1071271, "y": 32}, {"x": 1071274, "y": 31}, {"x": 1071277, "y": 30}, {"x": 1071288, "y": 29}, {"x": 1071293, "y": 28}, {"x": 1071305, "y": 27}, {"x": 1071314, "y": 26}, {"x": 1071324, "y": 25}, {"x": 1071331, "y": 24}, {"x": 1071339, "y": 23}, {"x": 1071352, "y": 22}, {"x": 1071374, "y": 21}, {"x": 1071393, "y": 20}, {"x": 1071416, "y": 19}, {"x": 1071435, "y": 18}, {"x": 1071461, "y": 17}, {"x": 1071492, "y": 16}, {"x": 1071532, "y": 15}, {"x": 1071585, "y": 14}, {"x": 1071655, "y": 13}, {"x": 1071727, "y": 12}, {"x": 1071846, "y": 11}, {"x": 1071991, "y": 10}, {"x": 1072209, "y": 9}, {"x": 1072497, "y": 8}, {"x": 1072924, "y": 7}, {"x": 1073665, "y": 6}, {"x": 1074813, "y": 5}, {"x": 1077036, "y": 4}, {"x": 1081798, "y": 3}, {"x": 1094956, "y": 2}, {"x": 1137282, "y": 1}], "21": [{"x": 1137283, "y": 1016}, {"x": 1137284, "y": 520}, {"x": 1137285, "y": 359}, {"x": 1137286, "y": 329}, {"x": 1137287, "y": 266}, {"x": 1137288, "y": 252}, {"x": 1137289, "y": 227}, {"x": 1137290, "y": 187}, {"x": 1137291, "y": 168}, {"x": 1137292, "y": 156}, {"x": 1137293, "y": 153}, {"x": 1137294, "y": 150}, {"x": 1137295, "y": 144}, {"x": 1137296, "y": 143}, {"x": 1137297, "y": 140}, {"x": 1137298, "y": 138}, {"x": 1137299, "y": 109}, {"x": 1137300, "y": 102}, {"x": 1137301, "y": 97}, {"x": 1137302, "y": 96}, {"x": 1137304, "y": 93}, {"x": 1137305, "y": 92}, {"x": 1137307, "y": 90}, {"x": 1137308, "y": 87}, {"x": 1137310, "y": 86}, {"x": 1137311, "y": 78}, {"x": 1137312, "y": 76}, {"x": 1137313, "y": 71}, {"x": 1137315, "y": 68}, {"x": 1137316, "y": 63}, {"x": 1137317, "y": 62}, {"x": 1137319, "y": 61}, {"x": 1137321, "y": 59}, {"x": 1137324, "y": 58}, {"x": 1137325, "y": 57}, {"x": 1137326, "y": 53}, {"x": 1137328, "y": 51}, {"x": 1137329, "y": 50}, {"x": 1137331, "y": 49}, {"x": 1137334, "y": 48}, {"x": 1137335, "y": 47}, {"x": 1137337, "y": 46}, {"x": 1137339, "y": 45}, {"x": 1137341, "y": 44}, {"x": 1137344, "y": 43}, {"x": 1137346, "y": 42}, {"x": 1137347, "y": 41}, {"x": 1137349, "y": 40}, {"x": 1137353, "y": 39}, {"x": 1137356, "y": 37}, {"x": 1137361, "y": 36}, {"x": 1137367, "y": 35}, {"x": 1137371, "y": 34}, {"x": 1137375, "y": 33}, {"x": 1137382, "y": 32}, {"x": 1137385, "y": 31}, {"x": 1137390, "y": 30}, {"x": 1137393, "y": 29}, {"x": 1137404, "y": 28}, {"x": 1137405, "y": 27}, {"x": 1137410, "y": 26}, {"x": 1137419, "y": 25}, {"x": 1137426, "y": 24}, {"x": 1137436, "y": 23}, {"x": 1137445, "y": 22}, {"x": 1137462, "y": 21}, {"x": 1137475, "y": 20}, {"x": 1137489, "y": 19}, {"x": 1137510, "y": 18}, {"x": 1137538, "y": 17}, {"x": 1137562, "y": 16}, {"x": 1137597, "y": 15}, {"x": 1137650, "y": 14}, {"x": 1137709, "y": 13}, {"x": 1137784, "y": 12}, {"x": 1137902, "y": 11}, {"x": 1138036, "y": 10}, {"x": 1138219, "y": 9}, {"x": 1138470, "y": 8}, {"x": 1138833, "y": 7}, {"x": 1139458, "y": 6}, {"x": 1140472, "y": 5}, {"x": 1142507, "y": 4}, {"x": 1146997, "y": 3}, {"x": 1159573, "y": 2}, {"x": 1200108, "y": 1}], "22": [{"x": 1200109, "y": 932}, {"x": 1200110, "y": 403}, {"x": 1200111, "y": 391}, {"x": 1200112, "y": 350}, {"x": 1200113, "y": 280}, {"x": 1200114, "y": 260}, {"x": 1200115, "y": 252}, {"x": 1200116, "y": 208}, {"x": 1200117, "y": 183}, {"x": 1200118, "y": 140}, {"x": 1200119, "y": 136}, {"x": 1200120, "y": 128}, {"x": 1200121, "y": 121}, {"x": 1200122, "y": 114}, {"x": 1200124, "y": 101}, {"x": 1200125, "y": 97}, {"x": 1200126, "y": 91}, {"x": 1200127, "y": 87}, {"x": 1200128, "y": 86}, {"x": 1200129, "y": 84}, {"x": 1200131, "y": 83}, {"x": 1200132, "y": 82}, {"x": 1200133, "y": 77}, {"x": 1200136, "y": 71}, {"x": 1200137, "y": 69}, {"x": 1200138, "y": 65}, {"x": 1200139, "y": 63}, {"x": 1200140, "y": 62}, {"x": 1200142, "y": 58}, {"x": 1200144, "y": 56}, {"x": 1200145, "y": 54}, {"x": 1200146, "y": 52}, {"x": 1200147, "y": 51}, {"x": 1200148, "y": 50}, {"x": 1200149, "y": 46}, {"x": 1200150, "y": 45}, {"x": 1200153, "y": 44}, {"x": 1200154, "y": 43}, {"x": 1200156, "y": 42}, {"x": 1200160, "y": 41}, {"x": 1200162, "y": 40}, {"x": 1200163, "y": 39}, {"x": 1200166, "y": 38}, {"x": 1200168, "y": 36}, {"x": 1200171, "y": 35}, {"x": 1200173, "y": 34}, {"x": 1200175, "y": 33}, {"x": 1200180, "y": 32}, {"x": 1200185, "y": 31}, {"x": 1200189, "y": 30}, {"x": 1200191, "y": 29}, {"x": 1200197, "y": 28}, {"x": 1200209, "y": 27}, {"x": 1200213, "y": 26}, {"x": 1200218, "y": 25}, {"x": 1200226, "y": 24}, {"x": 1200239, "y": 23}, {"x": 1200247, "y": 22}, {"x": 1200259, "y": 21}, {"x": 1200272, "y": 20}, {"x": 1200285, "y": 19}, {"x": 1200301, "y": 18}, {"x": 1200319, "y": 17}, {"x": 1200344, "y": 16}, {"x": 1200379, "y": 15}, {"x": 1200437, "y": 14}, {"x": 1200505, "y": 13}, {"x": 1200566, "y": 12}, {"x": 1200651, "y": 11}, {"x": 1200765, "y": 10}, {"x": 1200914, "y": 9}, {"x": 1201142, "y": 8}, {"x": 1201495, "y": 7}, {"x": 1202023, "y": 6}, {"x": 1202966, "y": 5}, {"x": 1204745, "y": 4}, {"x": 1208782, "y": 3}, {"x": 1220231, "y": 2}, {"x": 1257794, "y": 1}], "23": [{"x": 1257795, "y": 1453}, {"x": 1257796, "y": 907}, {"x": 1257797, "y": 361}, {"x": 1257798, "y": 295}, {"x": 1257799, "y": 283}, {"x": 1257800, "y": 280}, {"x": 1257801, "y": 240}, {"x": 1257802, "y": 218}, {"x": 1257803, "y": 179}, {"x": 1257804, "y": 177}, {"x": 1257805, "y": 136}, {"x": 1257806, "y": 128}, {"x": 1257807, "y": 123}, {"x": 1257808, "y": 117}, {"x": 1257809, "y": 100}, {"x": 1257810, "y": 94}, {"x": 1257811, "y": 82}, {"x": 1257812, "y": 77}, {"x": 1257813, "y": 75}, {"x": 1257815, "y": 74}, {"x": 1257816, "y": 71}, {"x": 1257817, "y": 66}, {"x": 1257819, "y": 61}, {"x": 1257820, "y": 60}, {"x": 1257821, "y": 59}, {"x": 1257822, "y": 58}, {"x": 1257823, "y": 56}, {"x": 1257824, "y": 55}, {"x": 1257825, "y": 54}, {"x": 1257826, "y": 53}, {"x": 1257827, "y": 52}, {"x": 1257828, "y": 51}, {"x": 1257829, "y": 49}, {"x": 1257831, "y": 48}, {"x": 1257832, "y": 47}, {"x": 1257834, "y": 46}, {"x": 1257836, "y": 45}, {"x": 1257838, "y": 44}, {"x": 1257841, "y": 43}, {"x": 1257845, "y": 42}, {"x": 1257847, "y": 41}, {"x": 1257848, "y": 40}, {"x": 1257850, "y": 39}, {"x": 1257852, "y": 38}, {"x": 1257853, "y": 37}, {"x": 1257855, "y": 36}, {"x": 1257856, "y": 35}, {"x": 1257859, "y": 34}, {"x": 1257863, "y": 33}, {"x": 1257864, "y": 32}, {"x": 1257867, "y": 31}, {"x": 1257868, "y": 30}, {"x": 1257873, "y": 29}, {"x": 1257879, "y": 28}, {"x": 1257884, "y": 27}, {"x": 1257889, "y": 26}, {"x": 1257892, "y": 25}, {"x": 1257905, "y": 24}, {"x": 1257912, "y": 23}, {"x": 1257917, "y": 22}, {"x": 1257927, "y": 21}, {"x": 1257936, "y": 20}, {"x": 1257951, "y": 19}, {"x": 1257962, "y": 18}, {"x": 1257985, "y": 17}, {"x": 1258003, "y": 16}, {"x": 1258031, "y": 15}, {"x": 1258062, "y": 14}, {"x": 1258110, "y": 13}, {"x": 1258160, "y": 12}, {"x": 1258235, "y": 11}, {"x": 1258333, "y": 10}, {"x": 1258471, "y": 9}, {"x": 1258654, "y": 8}, {"x": 1258935, "y": 7}, {"x": 1259382, "y": 6}, {"x": 1260259, "y": 5}, {"x": 1261870, "y": 4}, {"x": 1265570, "y": 3}, {"x": 1276180, "y": 2}, {"x": 1310680, "y": 1}]}